together/__init__.py
together/abstract/__init__.py
together/abstract/api_requestor.py
together/cli/__init__.py
together/cli/api/__init__.py
together/cli/api/chat.py
together/cli/api/completions.py
together/cli/api/endpoints.py
together/cli/api/evaluation.py
together/cli/api/files.py
together/cli/api/finetune.py
together/cli/api/images.py
together/cli/api/models.py
together/cli/api/utils.py
together/cli/cli.py
together/client.py
together/constants.py
together/error.py
together/filemanager.py
together/legacy/__init__.py
together/legacy/base.py
together/legacy/complete.py
together/legacy/embeddings.py
together/legacy/files.py
together/legacy/finetune.py
together/legacy/images.py
together/legacy/models.py
together/resources/__init__.py
together/resources/audio/__init__.py
together/resources/audio/speech.py
together/resources/audio/transcriptions.py
together/resources/audio/translations.py
together/resources/audio/voices.py
together/resources/batch.py
together/resources/chat/__init__.py
together/resources/chat/completions.py
together/resources/code_interpreter.py
together/resources/completions.py
together/resources/embeddings.py
together/resources/endpoints.py
together/resources/evaluation.py
together/resources/files.py
together/resources/finetune.py
together/resources/images.py
together/resources/models.py
together/resources/rerank.py
together/resources/videos.py
together/together_response.py
together/types/__init__.py
together/types/abstract.py
together/types/audio_speech.py
together/types/batch.py
together/types/chat_completions.py
together/types/code_interpreter.py
together/types/common.py
together/types/completions.py
together/types/embeddings.py
together/types/endpoints.py
together/types/error.py
together/types/evaluation.py
together/types/files.py
together/types/finetune.py
together/types/images.py
together/types/models.py
together/types/rerank.py
together/types/videos.py
together/utils/__init__.py
together/utils/_log.py
together/utils/api_helpers.py
together-1.5.35.dist-info/METADATA
together-1.5.35.dist-info/WHEEL
together-1.5.35.dist-info/entry_points.txt
together-1.5.35.dist-info/licenses/LICENSE
together-1.5.35.dist-info/RECORD
