Metadata-Version: 2.4
Name: together
Version: 1.5.35
Summary: Python client for Together's Cloud Platform! Note: SDK 2.0 is now available at https://github.com/togethercomputer/together-py
License: Apache-2.0
License-File: LICENSE
Author: Together AI
Author-email: support@together.ai
Requires-Python: >=3.10,<4.0
Classifier: License :: OSI Approved :: Apache Software License
Classifier: Operating System :: POSIX :: Linux
Classifier: Programming Language :: Python :: 3
Classifier: Programming Language :: Python :: 3.10
Classifier: Programming Language :: Python :: 3.11
Classifier: Programming Language :: Python :: 3.12
Classifier: Programming Language :: Python :: 3.13
Classifier: Programming Language :: Python :: 3.14
Provides-Extra: pyarrow
Requires-Dist: aiohttp (>=3.9.3,<4.0.0)
Requires-Dist: black (>=25.9.0,<26.0.0)
Requires-Dist: click (>=8.1.7,<9.0.0)
Requires-Dist: eval-type-backport (>=0.1.3,<0.3.0)
Requires-Dist: filelock (>=3.13.1,<4.0.0)
Requires-Dist: numpy (>=1.23.5) ; python_version < "3.12"
Requires-Dist: numpy (>=1.26.0) ; python_version >= "3.12"
Requires-Dist: pillow (>=11.1.0,<12.0.0)
Requires-Dist: pyarrow (>=10.0.1) ; extra == "pyarrow"
Requires-Dist: pydantic (>=2.6.3,<3.0.0)
Requires-Dist: requests (>=2.31.0,<3.0.0)
Requires-Dist: rich (>=13.8.1,<15.0.0)
Requires-Dist: tabulate (>=0.9.0,<0.10.0)
Requires-Dist: tqdm (>=4.66.2,<5.0.0)
Requires-Dist: typer (>=0.9,<0.20)
Project-URL: Bug Tracker, https://github.com/togethercomputer/together-python/issues
Project-URL: Homepage, https://github.com/togethercomputer/together-python
Project-URL: Repository, https://github.com/togethercomputer/together-python
